wilibs/__init__.py
wilibs-0.0.2.dist-info/LICENSE
wilibs-0.0.2.dist-info/METADATA
wilibs-0.0.2.dist-info/WHEEL
wilibs-0.0.2.dist-info/top_level.txt
wilibs-0.0.2.dist-info/RECORD
