Metadata-Version: 2.1
Name: wilibs
Version: 0.0.2
Summary: Wilib
Home-page: https://github.com/revotechUET/wilibs
Author: Revotech
Author-email: support@i2g.cloud
License: UNKNOWN
Platform: UNKNOWN
Classifier: Programming Language :: Python :: 3
Classifier: License :: OSI Approved :: MIT License
Classifier: Operating System :: OS Independent
Requires-Python: >=3.6
